mixin/__init__.py
mixin/annotate.py
mixin/api.py
mixin/callback.py
mixin/impl.py
mixin/util.py
pymixin-1.1.1.dist-info/LICENSE
pymixin-1.1.1.dist-info/METADATA
pymixin-1.1.1.dist-info/WHEEL
pymixin-1.1.1.dist-info/top_level.txt
pymixin-1.1.1.dist-info/RECORD
